seqmodels/__init__.py
seqmodels/_utils.py
seqmodels/base/__init__.py
seqmodels/base/_architectures.py
seqmodels/base/_blocks.py
seqmodels/base/_construct.py
seqmodels/base/_initializers.py
seqmodels/base/_layers.py
seqmodels/base/_losses.py
seqmodels/base/_metrics.py
seqmodels/base/_modules.py
seqmodels/base/_optimizers.py
seqmodels/base/_regularizers.py
seqmodels/base/_schedulers.py
seqmodels/base/_towers.py
seqmodels/zoo/__init__.py
seqmodels/zoo/_config.py
seqmodels/zoo/_load.py
seqmodels/zoo/cre_activity_predictors/deepstarr.yaml
seqmodels/zoo/regulatory_classifiers/basset.yaml
seqmodels/zoo/regulatory_classifiers/danq.yaml
seqmodels/zoo/regulatory_classifiers/deepsea.yaml
seqmodels/zoo/regulatory_classifiers/factorized_basset.yaml
seqmodels/zoo/regulatory_classifiers/satori.yaml
seqmodels/zoo/single_cell_atac/deepmel.yaml
seqmodels/zoo/single_cell_atac/deepmel2.yaml
seqmodels/zoo/single_cell_atac/scbasset.yaml
seqmodels/zoo/tf_rbp_predictors/deepbind_rbp.yaml
seqmodels/zoo/tf_rbp_predictors/deepbind_tf.yaml
seqmodels/zoo/tf_rbp_predictors/residual_bind.yaml
seqmodels-0.0.3.dist-info/LICENSE
seqmodels-0.0.3.dist-info/METADATA
seqmodels-0.0.3.dist-info/WHEEL
seqmodels-0.0.3.dist-info/RECORD
