Metadata-Version: 2.1
Name: seqmodels
Version: 0.0.3
Summary: Building sequence-to-function machine learning models
License: MIT
Author: adamklie
Author-email: aklie@ucsd.edu
Requires-Python: >=3.8,<3.12
Classifier: License :: OSI Approved :: MIT License
Classifier: Programming Language :: Python :: 3
Classifier: Programming Language :: Python :: 3.8
Classifier: Programming Language :: Python :: 3.9
Classifier: Programming Language :: Python :: 3.10
Classifier: Programming Language :: Python :: 3.11
Requires-Dist: bpnet-lite (>=0.6.0)
Requires-Dist: einops (>=0.6.1)
Requires-Dist: pytorch-lightning (>=2.0.0,<3.0.0)
Requires-Dist: pyyaml (>=6.0.1,<7.0.0)
Requires-Dist: torch (>=1.12.0)
Requires-Dist: torchinfo (>=1.8.0)
Requires-Dist: tqdm (>=4.65.0,<5.0.0)
